[[null,null,{"Age":"25-65","Biopsy Result Before Treatment":"CIN1","Margins":"Negative","Treatment":"Excision","Management":"6-month follow-up","Notes":"HPV-based testing in 6 months"},{"Age":"25-65","Biopsy Result Before Treatment":"CIN2","Margins":"Negative","Treatment":"Excision","Management":"6-month follow-up","Notes":"HPV-based testing in 6 months"},{"Age":"25-65","Biopsy Result Before Treatment":"CIN3","Margins":"Negative","Treatment":"Excision","Management":"6-month follow-up","Notes":"HPV-based testing in 6 months"},{"Age":"21-24","Biopsy Result Before Treatment":"CIN1","Treatment":"Excision","Management":"6-month follow-up","Notes":"Cytology in 6 months"},{"Age":"21-24","Biopsy Result Before Treatment":"CIN2","Treatment":"Excision","Management":"6-month follow-up","Notes":"Cytology in 6 months"},{"Age":"21-24","Biopsy Result Before Treatment":"CIN3","Treatment":"Excision","Management":"6-month follow-up","Notes":"Cytology in 6 months"},{"Age":"25-65","Biopsy Result Before Treatment":"CIN1","Treatment":"Ablation","Management":"6-month follow-up","Notes":"HPV-based testing in 6 months"},{"Age":"25-65","Biopsy Result Before Treatment":"CIN2","Treatment":"Ablation","Management":"6-month follow-up","Notes":"HPV-based testing in 6 months"},{"Age":"25-65","Biopsy Result Before Treatment":"CIN3","Treatment":"Ablation","Management":"6-month follow-up","Notes":"HPV-based testing in 6 months"},{"Age":"21-24","Biopsy Result Before Treatment":"CIN1","Treatment":"Ablation","Management":"6-month follow-up","Notes":"Cytology in 6 months"},{"Age":"21-24","Biopsy Result Before Treatment":"CIN2","Treatment":"Ablation","Management":"6-month follow-up","Notes":"Cytology in 6 months"},{"Age":"21-24","Biopsy Result Before Treatment":"CIN3","Treatment":"Ablation","Management":"6-month follow-up","Notes":"Cytology in 6 months"},{"Age":"21-65","Biopsy Result Before Treatment":"CIN2","Margins":"Positive","Treatment":"Excision","Management":"6-month follow-up","Notes":"HPV-based testing in 6 months (preferred), or colposcopy and ECC in 6 months (acceptable)"},{"Age":"21-65","Biopsy Result Before Treatment":"CIN2","Margins":"Positive","Treatment":"Excision","Management":"6-month follow-up","Notes":"HPV-based testing in 6 months (preferred), or colposcopy and ECC in 6 months (acceptable)"},{"Age":"21-65","Biopsy Result Before Treatment":"CIN2","Margins":"Positive","Treatment":"Excision","Management":"6-month follow-up","Notes":"HPV-based testing in 6 months (preferred), or colposcopy and ECC in 6 months (acceptable)"},{"Age":"21-65","Biopsy Result Before Treatment":"CIN3","Margins":"Positive","Treatment":"Excision","Management":"6-month follow-up","Notes":"HPV-based testing in 6 months (preferred), or colposcopy and ECC in 6 months (acceptable)"},{"Age":"21-65","Biopsy Result Before Treatment":"CIN3","Margins":"Positive","Treatment":"Excision","Management":"6-month follow-up","Notes":"HPV-based testing in 6 months (preferred), or colposcopy and ECC in 6 months (acceptable)"},{"Age":"21-65","Biopsy Result Before Treatment":"CIN3","Margins":"Positive","Treatment":"Excision","Management":"6-month follow-up","Notes":"HPV-based testing in 6 months (preferred), or colposcopy and ECC in 6 months (acceptable)"}]]